python_monads/__init__.py
python_monads/either.py
python_monads/maybe.py
tests/__init__.py
tests/test_either.py
tests/test_maybe.py
python_monads-0.0.8.dist-info/LICENSE
python_monads-0.0.8.dist-info/METADATA
python_monads-0.0.8.dist-info/WHEEL
python_monads-0.0.8.dist-info/top_level.txt
python_monads-0.0.8.dist-info/RECORD
