Metadata-Version: 2.2
Name: python-monads
Version: 0.0.8
Summary: Either and Maybe monads for Python
Author-email: Pol Dellaiera <pol.dellaiera@protonmail.com>
License: The MIT License (MIT)
Project-URL: Homepage, https://github.com/drupol/python-monads
Project-URL: Repository, https://github.com/drupol/python-monads.git
Project-URL: Issues, https://github.com/drupol/python-monads/issues
Keywords: monad,functional-programmtion,complexity
Classifier: Intended Audience :: Developers
Classifier: License :: OSI Approved :: MIT License
Classifier: Programming Language :: Python :: 3.8
Classifier: Programming Language :: Python :: 3.9
Classifier: Programming Language :: Python :: 3.11
Classifier: Programming Language :: Python :: 3.12
Classifier: Programming Language :: Python :: 3.13
Classifier: Topic :: Software Development :: Libraries :: Python Modules
Requires-Python: >=3.11
License-File: LICENSE
